gspread_dataframe.py
gspread_dataframe-4.0.0.dist-info/LICENSE
gspread_dataframe-4.0.0.dist-info/METADATA
gspread_dataframe-4.0.0.dist-info/WHEEL
gspread_dataframe-4.0.0.dist-info/top_level.txt
gspread_dataframe-4.0.0.dist-info/zip-safe
gspread_dataframe-4.0.0.dist-info/RECORD
