Metadata-Version: 2.1
Name: gspread-dataframe
Version: 4.0.0
Summary: Read/write gspread worksheets using pandas DataFrames
Home-page: https://github.com/robin900/gspread-dataframe
Author: Robin Thomas
Author-email: rthomas900@gmail.com
License: MIT
Keywords: spreadsheets,google-spreadsheets,pandas,dataframe
Classifier: Programming Language :: Python
Classifier: Programming Language :: Python :: 3
Classifier: License :: OSI Approved :: MIT License
Classifier: Operating System :: OS Independent
Classifier: Development Status :: 5 - Production/Stable
Classifier: Intended Audience :: Developers
Classifier: Intended Audience :: Science/Research
Classifier: Topic :: Office/Business :: Financial :: Spreadsheet
Classifier: Topic :: Software Development :: Libraries :: Python Modules
License-File: LICENSE
